pyreadpartitions/__init__.py
pyreadpartitions/__main__.py
pyreadpartitions-1.1.1.dist-info/LICENSE
pyreadpartitions-1.1.1.dist-info/METADATA
pyreadpartitions-1.1.1.dist-info/WHEEL
pyreadpartitions-1.1.1.dist-info/entry_points.txt
pyreadpartitions-1.1.1.dist-info/top_level.txt
pyreadpartitions-1.1.1.dist-info/RECORD
